nqrduck_spectrometer_simulator/__init__.py
nqrduck_spectrometer_simulator/controller.py
nqrduck_spectrometer_simulator/model.py
nqrduck_spectrometer_simulator/simulator.py
nqrduck_spectrometer_simulator/view.py
nqrduck_spectrometer_simulator/resources/simulator.ini
nqrduck_spectrometer_simulator-0.0.6.dist-info/METADATA
nqrduck_spectrometer_simulator-0.0.6.dist-info/WHEEL
nqrduck_spectrometer_simulator-0.0.6.dist-info/entry_points.txt
nqrduck_spectrometer_simulator-0.0.6.dist-info/licenses/LICENSE
nqrduck_spectrometer_simulator-0.0.6.dist-info/RECORD
