Metadata-Version: 2.4
Name: nqrduck-spectrometer-simulator
Version: 0.0.6
Summary: A submodule for the nqrduck-spectrometer module which implements the functionality of a NQR bloch simulator. This should enable easy simulation of NQR experiments.
Project-URL: Homepage, https://nqrduck.cool
Project-URL: Bug Tracker, https://git.private.coffee/nqrduck/nqrduck-spectrometer-simulator/issues
Project-URL: Source Code, https://git.private.coffee/nqrduck/nqrduck-spectrometer-simulator
Author-email: jupfi <support@nqrduck.cool>
License: MIT License
License-File: LICENSE
Classifier: License :: OSI Approved :: MIT License
Classifier: Operating System :: OS Independent
Classifier: Programming Language :: Python :: 3
Requires-Python: >=3.10
Requires-Dist: nqr-blochsimulator
Requires-Dist: nqrduck-spectrometer
Requires-Dist: numpy
Requires-Dist: pyqt6
Requires-Dist: quackseq-simulator
